colmap_rerun/__init__.py
colmap_rerun/cli/__init__.py
colmap_rerun/cli/main.py
colmap_rerun/core/__init__.py
colmap_rerun/core/read_write_model.py
colmap_rerun/core/reconstruction.py
colmap_rerun/visualization/__init__.py
colmap_rerun/visualization/visualizer.py
colmap_rerun-1.0.2.dist-info/licenses/LICENSE
colmap_rerun-1.0.2.dist-info/METADATA
colmap_rerun-1.0.2.dist-info/WHEEL
colmap_rerun-1.0.2.dist-info/entry_points.txt
colmap_rerun-1.0.2.dist-info/top_level.txt
colmap_rerun-1.0.2.dist-info/RECORD
