Metadata-Version: 2.4
Name: colmap-rerun
Version: 1.0.2
Summary: Visualize COLMAP sparse reconstruction output using Rerun
Author-email: Vincentqyw <alpha.vincentqin@gmail.com>
License: MIT
Classifier: Programming Language :: Python :: 3
Classifier: License :: OSI Approved :: MIT License
Classifier: Operating System :: OS Independent
Requires-Python: >=3.8
License-File: LICENSE
Requires-Dist: opencv-python>=4.6
Requires-Dist: numpy>=1.21
Requires-Dist: rerun-sdk>=0.9
Requires-Dist: tqdm>=4.0
Provides-Extra: test
Requires-Dist: pytest>=7.0; extra == "test"
Requires-Dist: pytest-cov>=4.0; extra == "test"
Dynamic: license-file
